setup.py
dockerrun/__init__.py
dockerrun/client.py
dockerrun.egg-info/PKG-INFO
dockerrun.egg-info/SOURCES.txt
dockerrun.egg-info/dependency_links.txt
dockerrun.egg-info/requires.txt
dockerrun.egg-info/top_level.txt