Metadata-Version: 1.0
Name: dockerrun
Version: 0.1.2
Summary: A dead simple Python library for running Docker commands
Home-page: https://github.com/bfirsh/dockerrun
Author: Ben Firshman
Author-email: ben@firshman.co.uk
License: UNKNOWN
Platform: UNKNOWN
